{
  "project_info": {
    "project_number": "733223963023",
    "project_id": "vault-9cbbd",
    "storage_bucket": "vault-9cbbd.firebasestorage.app"
  },
  "client": [
    {
      "client_info": {
        "mobilesdk_app_id": "1:733223963023:android:254ac31842dc70fcf7e3fa",
        "android_client_info": {
          "package_name": "com.enekocm.securevault"
        }
      },
      "oauth_client": [
        {
          "client_id": "733223963023-0p51jeorscjgk2g6hrah30f4f391ga04.apps.googleusercontent.com",
          "client_type": 1,
          "android_info": {
            "package_name": "com.enekocm.securevault",
            "certificate_hash": "70b1e93ec850415e9ecae05588218e8252e00971"
          }
        },
        {
          "client_id": "733223963023-8t6alkns5o0h632m4amm0r2mkamb27sb.apps.googleusercontent.com",
          "client_type": 3
        }
      ],
      "api_key": [
        {
          "current_key": "AIzaSyDje2cPqlx1oSgVDXOifjUc7J_doO-mvNs"
        }
      ],
      "services": {
        "appinvite_service": {
          "other_platform_oauth_client": [
            {
              "client_id": "733223963023-8t6alkns5o0h632m4amm0r2mkamb27sb.apps.googleusercontent.com",
              "client_type": 3
            }
          ]
        }
      }
    }
  ],
  "configuration_version": "1"
}